plover_clr_trans_state.py
plover_clr_trans_state-0.0.0.dist-info/LICENSE
plover_clr_trans_state-0.0.0.dist-info/METADATA
plover_clr_trans_state-0.0.0.dist-info/WHEEL
plover_clr_trans_state-0.0.0.dist-info/entry_points.txt
plover_clr_trans_state-0.0.0.dist-info/top_level.txt
plover_clr_trans_state-0.0.0.dist-info/RECORD
