Metadata-Version: 2.1
Name: plover-clr-trans-state
Version: 0.0.0
Summary: Plover plugin that adds a command to clear the translation state
Home-page: https://github.com/Kenny2github/plover-clr-trans-state
Author: AbyxDev
License: MIT
Keywords: plover plover_plugin
Platform: UNKNOWN
Classifier: Environment :: Plugins
Classifier: License :: OSI Approved :: MIT License
Classifier: Operating System :: OS Independent
Classifier: Programming Language :: Python :: 3
